bamsalvage/__init__.py
bamsalvage/_bamsalvage.py
bamsalvage-0.1.7.dist-info/METADATA
bamsalvage-0.1.7.dist-info/WHEEL
bamsalvage-0.1.7.dist-info/entry_points.txt
bamsalvage-0.1.7.dist-info/licenses/LICENSE
bamsalvage-0.1.7.dist-info/RECORD
