Metadata-Version: 2.1
Name: bamsalvage
Version: 0.1.7
Summary: Sequence salvaging script from corrupted BAM files
Project-URL: Homepage, https://pypi.org/project/bamsalvage/
Author-email: "Takaho A. Endo" <takaho.endo@gmail.com>
License-File: LICENSE
Classifier: License :: OSI Approved :: MIT License
Classifier: Operating System :: OS Independent
Classifier: Programming Language :: Python :: 3
Requires-Python: >=3.7
Requires-Dist: mgzip
Requires-Dist: numba
Requires-Dist: numpy
